lgsv/__init__.py
lgsv/cli.py
lgsv/log.py
lgsv/luogu.py
lgsv/setting.py
lgsv-0.1.4.dist-info/LICENSE
lgsv-0.1.4.dist-info/METADATA
lgsv-0.1.4.dist-info/WHEEL
lgsv-0.1.4.dist-info/entry_points.txt
lgsv-0.1.4.dist-info/RECORD
