Metadata-Version: 2.3
Name: lgsv
Version: 0.1.4
Summary: 爬取洛谷题目并用 markdown 格式保存
License: MIT
Author: Sving1024
Author-email: sving1024@outlook.com
Requires-Python: >=3.11,<4.0
Classifier: License :: OSI Approved :: MIT License
Classifier: Operating System :: OS Independent
Classifier: Programming Language :: Python :: 3
Classifier: Programming Language :: Python :: 3.11
Classifier: Programming Language :: Python :: 3.12
Classifier: Programming Language :: Python :: 3.13
Requires-Dist: httpx (>=0.27.2,<0.28.0)
Requires-Dist: pypandoc (>=1.13,<2.0)
Requires-Dist: tomli (>=2.0.1,<3.0.0)
